brainsmash/__init__.py
brainsmash/config.py
brainsmash/data/CortexSubcortex_ColeAnticevic_NetPartition_wSubcorGSR_netassignments_LR.dlabel.nii
brainsmash/mapgen/__init__.py
brainsmash/mapgen/base.py
brainsmash/mapgen/eval.py
brainsmash/mapgen/kernels.py
brainsmash/mapgen/memmap.py
brainsmash/mapgen/sampled.py
brainsmash/mapgen/stats.py
brainsmash/utils/__init__.py
brainsmash/utils/checks.py
brainsmash/utils/dataio.py
brainsmash/workbench/__init__.py
brainsmash/workbench/geo.py
brainsmash/workbench/io.py
brainsmash/workbench/surf.py
brainsmash-0.11.0.dist-info/LICENSE
brainsmash-0.11.0.dist-info/METADATA
brainsmash-0.11.0.dist-info/WHEEL
brainsmash-0.11.0.dist-info/top_level.txt
brainsmash-0.11.0.dist-info/RECORD
