Metadata-Version: 2.1
Name: brainsmash
Version: 0.11.0
Summary: Brain Surrogate Maps with Autocorrelated Spatial Heterogeneity.
Home-page: https://github.com/murraylab/brainsmash
Author: Joshua Burt
Author-email: joshua.burt@yale.edu
License: UNKNOWN
Platform: UNKNOWN
Classifier: Programming Language :: Python :: 3.7
Classifier: License :: OSI Approved :: GNU General Public License v3 (GPLv3)
Requires-Python: >=3
Requires-Dist: numpy
Requires-Dist: scikit-learn
Requires-Dist: pandas
Requires-Dist: scipy
Requires-Dist: matplotlib
Requires-Dist: nibabel
Requires-Dist: joblib
